twisted/plugins/pkgupload.py
txpkgupload/NEWS.txt
txpkgupload/__init__.py
txpkgupload/filesystem.py
txpkgupload/hooks.py
txpkgupload/plugin.py
txpkgupload/services.py
txpkgupload/twistedftp.py
txpkgupload/twistedsftp.py
txpkgupload/version.txt
txpkgupload/tests/__init__.py
txpkgupload/tests/filesystem.txt
txpkgupload/tests/test_filesystem.py
txpkgupload/tests/test_plugin.py
txpkgupload/tests/test_twistedsftp.py
txpkgupload/tests/txpkgupload-sftp
txpkgupload/tests/txpkgupload-sftp.pub
txpkgupload-0.5.dist-info/COPYING.txt
txpkgupload-0.5.dist-info/METADATA
txpkgupload-0.5.dist-info/WHEEL
txpkgupload-0.5.dist-info/top_level.txt
txpkgupload-0.5.dist-info/RECORD
