Metadata-Version: 2.1
Name: txpkgupload
Version: 0.5
Summary: Package upload server used by Launchpad.
Home-page: https://launchpad.net/txpkgupload
Download-URL: https://launchpad.net/txpkgupload/+download
Maintainer: LAZR Developers
Maintainer-email: lazr-developers@lists.launchpad.net
License: AGPL v3
Classifier: Development Status :: 5 - Production/Stable
Classifier: Intended Audience :: Developers
Classifier: License :: OSI Approved :: GNU Affero General Public License v3
Classifier: Operating System :: OS Independent
Classifier: Programming Language :: Python
Classifier: Programming Language :: Python :: 3
Classifier: Programming Language :: Python :: 3.5
Classifier: Programming Language :: Python :: 3.6
Classifier: Programming Language :: Python :: 3.7
Classifier: Programming Language :: Python :: 3.8
Requires-Python: >=3.5
License-File: COPYING.txt
Requires-Dist: FormEncode
Requires-Dist: lazr.sshserver (>=0.1.7)
Requires-Dist: oops-datedir-repo (>=0.0.21)
Requires-Dist: oops-twisted (>=0.0.7)
Requires-Dist: PyYAML
Requires-Dist: setuptools
Requires-Dist: six (>=1.12.0)
Requires-Dist: Twisted[conch_nacl]
Requires-Dist: zope.interface (>=3.6.0)
Requires-Dist: importlib-metadata ; python_version < "3.8"
Provides-Extra: test
Requires-Dist: fixtures ; extra == 'test'
Requires-Dist: testtools ; extra == 'test'
